brisk/__init__.py
brisk/cli/__init__.py
brisk/cli/cli.py
brisk/cli/cli_helpers.py
brisk/cli/environment.py
brisk/configuration/__init__.py
brisk/configuration/algorithm_collection.py
brisk/configuration/algorithm_wrapper.py
brisk/configuration/configuration.py
brisk/configuration/configuration_manager.py
brisk/configuration/experiment.py
brisk/configuration/experiment_factory.py
brisk/configuration/experiment_group.py
brisk/configuration/project.py
brisk/data/__init__.py
brisk/data/data_manager.py
brisk/data/data_split_info.py
brisk/data/data_splits.py
brisk/data/preprocessing.py
brisk/defaults/__init__.py
brisk/defaults/classification_algorithms.py
brisk/defaults/classification_metrics.py
brisk/defaults/regression_algorithms.py
brisk/defaults/regression_metrics.py
brisk/evaluation/__init__.py
brisk/evaluation/evaluation_manager.py
brisk/evaluation/evaluators/base.py
brisk/evaluation/evaluators/builtin/__init__.py
brisk/evaluation/evaluators/builtin/classification_measures.py
brisk/evaluation/evaluators/builtin/classification_plots.py
brisk/evaluation/evaluators/builtin/common_measures.py
brisk/evaluation/evaluators/builtin/common_plots.py
brisk/evaluation/evaluators/builtin/dataset_measures.py
brisk/evaluation/evaluators/builtin/dataset_plots.py
brisk/evaluation/evaluators/builtin/optimization.py
brisk/evaluation/evaluators/builtin/regression_plots.py
brisk/evaluation/evaluators/dataset_measure_evaluator.py
brisk/evaluation/evaluators/dataset_plot_evaluator.py
brisk/evaluation/evaluators/measure_evaluator.py
brisk/evaluation/evaluators/plot_evaluator.py
brisk/evaluation/evaluators/registry.py
brisk/evaluation/metric_manager.py
brisk/evaluation/metric_wrapper.py
brisk/reporting/__init__.py
brisk/reporting/components/experiment_group_card.html
brisk/reporting/components/navbar.html
brisk/reporting/components/plot.html
brisk/reporting/components/table.html
brisk/reporting/formatting.py
brisk/reporting/js/core/app.js
brisk/reporting/js/renderers/dataset_page.js
brisk_ml-1.1.0.dist-info/METADATA
brisk_ml-1.1.0.dist-info/WHEEL
brisk_ml-1.1.0.dist-info/entry_points.txt
brisk_ml-1.1.0.dist-info/RECORD
