Metadata-Version: 2.1
Name: brisk-ml
Version: 1.1.0
Summary: A framework that helps train machine learning models using sklearn.
Author: BFieguth
Author-email: bfieguth@uoguelph.ca
Requires-Python: >=3.10,<4.0
Classifier: Programming Language :: Python :: 3
Classifier: Programming Language :: Python :: 3.10
Classifier: Programming Language :: Python :: 3.11
Classifier: Programming Language :: Python :: 3.12
Requires-Dist: click (>=8.1.7,<9.0.0)
Requires-Dist: jinja2 (>=3.1.4,<4.0.0)
Requires-Dist: joblib (>=1.4.2,<2.0.0)
Requires-Dist: kaleido (>=1.0.0,<2.0.0)
Requires-Dist: matplotlib (>=3.9.2,<4.0.0)
Requires-Dist: numpy (>=2.1.2,<3.0.0)
Requires-Dist: openpyxl (>=3.1.5,<4.0.0)
Requires-Dist: pandas (>=2.2.3,<3.0.0)
Requires-Dist: plotly (>=6.1.0,<7.0.0)
Requires-Dist: plotnine (>=0.14.4,<0.15.0)
Requires-Dist: pydantic (>=2.11.7,<3.0.0)
Requires-Dist: scikit-learn (>=1.5.1,<2.0.0)
Requires-Dist: seaborn (>=0.13.2,<0.14.0)
Requires-Dist: shap (>=0.48.0,<0.49.0)
Requires-Dist: toml (>=0.10.2,<0.11.0)
Requires-Dist: tqdm (>=4.66.5,<5.0.0)
